dartsass/__init__.py
dartsass/_main.py
dartsass/_options.py
dartsass/sass/linux-arm64/dart-sass/sass
dartsass/sass/linux-arm64/dart-sass/src/LICENSE
dartsass/sass/linux-ia32/dart-sass/sass
dartsass/sass/linux-ia32/dart-sass/src/LICENSE
dartsass/sass/linux-ia32/dart-sass/src/dart
dartsass/sass/linux-ia32/dart-sass/src/sass.snapshot
dartsass/sass/linux-x64/dart-sass/sass
dartsass/sass/linux-x64/dart-sass/src/LICENSE
dartsass/sass/macos-arm64/dart-sass/sass
dartsass/sass/macos-arm64/dart-sass/src/LICENSE
dartsass/sass/macos-arm64/dart-sass/src/dart
dartsass/sass/macos-arm64/dart-sass/src/sass.snapshot
dartsass/sass/macos-x64/dart-sass/sass
dartsass/sass/macos-x64/dart-sass/src/LICENSE
dartsass/sass/macos-x64/dart-sass/src/dart
dartsass/sass/macos-x64/dart-sass/src/sass.snapshot
dartsass/sass/windows-ia32/dart-sass/sass.bat
dartsass/sass/windows-ia32/dart-sass/src/LICENSE
dartsass/sass/windows-ia32/dart-sass/src/dart.exe
dartsass/sass/windows-ia32/dart-sass/src/sass.snapshot
dartsass/sass/windows-x64/dart-sass/sass.bat
dartsass/sass/windows-x64/dart-sass/src/LICENSE
dartsass/sass/windows-x64/dart-sass/src/dart.exe
dartsass/sass/windows-x64/dart-sass/src/sass.snapshot
dart_sass-0.5.2.dist-info/LICENSE
dart_sass-0.5.2.dist-info/METADATA
dart_sass-0.5.2.dist-info/WHEEL
dart_sass-0.5.2.dist-info/top_level.txt
dart_sass-0.5.2.dist-info/RECORD
