Metadata-Version: 2.1
Name: dart-sass
Version: 0.5.2
Summary: A wrapper around Dart Sass (https://sass-lang.com/dart-sass)
Home-page: https://github.com/dumdoo/py-dart-sass
Author: dumdoo
License: MIT
Project-URL: Bug Tracker, https://github.com/dumdoo/py-dart-sass/issues
Platform: UNKNOWN
Classifier: Programming Language :: Python :: 3.10
Classifier: License :: OSI Approved :: MIT License
Classifier: Operating System :: POSIX :: Linux
Classifier: Operating System :: MacOS
Classifier: Operating System :: Microsoft :: Windows
Classifier: Development Status :: 3 - Alpha
Classifier: Intended Audience :: Developers
Requires-Python: >=3.10
License-File: LICENSE
